{
  "author": "RedHeart",
  "gameTypeIdentifier": null,
  "version": null,
  "thumbnailURL": "https://github.com/Provenance-Emu/skins/releases/download/thumbnails/b871536af1e97cb0.png",
  "screenshotURLs": [],
  "tags": [],
  "deviceSupport": [],
  "downloadCount": null,
  "rating": null,
  "lastUpdated": null,
  "fileSize": null,
  "submittedBy": null,
  "submittedAt": null,
  "name": "Pokemon: Cinccino GBA by RedHeart",
  "downloadURL": "https://deltastyles.com/files/skins/616/Cinccino GBA by RedHeart.deltaskin",
  "systems": [
    "gba"
  ],
  "source": "deltastyles.com",
  "id": "b871536af1e97cb0"
}
