{
  "author": "antnoz",
  "gameTypeIdentifier": null,
  "version": null,
  "thumbnailURL": "https://github.com/Provenance-Emu/skins/releases/download/thumbnails/7408a18ddd47e846.png",
  "screenshotURLs": [],
  "tags": [],
  "deviceSupport": [],
  "downloadCount": null,
  "rating": null,
  "lastUpdated": null,
  "fileSize": null,
  "submittedBy": null,
  "submittedAt": null,
  "name": "Minimal Red Genesis Skin",
  "downloadURL": "https://deltastyles.com/files/skins/638/MinimalRedGenesis.deltaskin",
  "systems": [
    "genesis"
  ],
  "source": "deltastyles.com",
  "id": "7408a18ddd47e846"
}
