{
  "author": "moulinsoki",
  "gameTypeIdentifier": null,
  "version": null,
  "thumbnailURL": "https://github.com/Provenance-Emu/skins/releases/download/thumbnails/7594002224508649.png",
  "screenshotURLs": [],
  "tags": [],
  "deviceSupport": [],
  "downloadCount": null,
  "rating": null,
  "lastUpdated": null,
  "fileSize": null,
  "submittedBy": null,
  "submittedAt": null,
  "name": "One Handed Master System",
  "downloadURL": "https://deltastyles.com/files/skins/672/One Handed MasterSystem.manicskin",
  "systems": [
    "masterSystem"
  ],
  "source": "deltastyles.com",
  "id": "7594002224508649"
}
