{
  "author": "ark",
  "gameTypeIdentifier": null,
  "version": null,
  "thumbnailURL": "https://github.com/Provenance-Emu/skins/releases/download/thumbnails/a4bf3ba9c8db5023.png",
  "screenshotURLs": [],
  "tags": [],
  "deviceSupport": [],
  "downloadCount": null,
  "rating": null,
  "lastUpdated": null,
  "fileSize": null,
  "submittedBy": null,
  "submittedAt": null,
  "name": "WiiUDS White - A DS Skin with dual control input",
  "downloadURL": "https://deltastyles.com/download-files.php?id=234",
  "systems": [
    "nds"
  ],
  "source": "deltastyles.com",
  "id": "a4bf3ba9c8db5023"
}
