{
  "id": "d3e536deb9b62e08",
  "name": "SNES Pocket",
  "author": "starvingartist",
  "systems": [
    "snes"
  ],
  "downloadURL": "https://deltastyles.com/download-files.php?id=559",
  "thumbnailURL": "https://github.com/Provenance-Emu/skins/releases/download/thumbnails/d3e536deb9b62e08.png",
  "screenshotURLs": [],
  "description": null,
  "tags": [
    "edge-to-edge",
    "fast-forward",
    "quick-save-load",
    "portrait",
    "landscape",
    "manic"
  ],
  "source": "deltastyles.com",
  "version": null,
  "gameTypeIdentifier": null,
  "deviceSupport": [],
  "downloadCount": null,
  "rating": null,
  "lastUpdated": "2025-12-26",
  "fileSize": null,
  "submittedBy": null,
  "submittedAt": null
}
